{
    "version": "0.6.0",
    "architecture": {
        "64bit": {
            "url": "https://github.com/NicholasCullenCooper/csaw/releases/download/v0.6.0/csaw_0.6.0_windows_amd64.zip",
            "bin": [
                "csaw.exe"
            ],
            "hash": "a455a6ed4013af4e0d956db46381354db2015ebb5220b62fb300326f395c9744"
        },
        "arm64": {
            "url": "https://github.com/NicholasCullenCooper/csaw/releases/download/v0.6.0/csaw_0.6.0_windows_arm64.zip",
            "bin": [
                "csaw.exe"
            ],
            "hash": "aa25140540cb9be88d4d0010f01999bb36e1347473e562fe79545ce7cc1c2d19"
        }
    },
    "homepage": "https://github.com/NicholasCullenCooper/csaw",
    "license": "MIT",
    "description": "Mount, not install. AI workspace configuration from git-backed registries."
}
