{
    "version": "0.6.1",
    "architecture": {
        "64bit": {
            "url": "https://github.com/NicholasCullenCooper/csaw/releases/download/v0.6.1/csaw_0.6.1_windows_amd64.zip",
            "bin": [
                "csaw.exe"
            ],
            "hash": "a7ecd84f51954af05e50dd69b5ceea77cff0d16846ce6cf4cbb681a4a3c66238"
        },
        "arm64": {
            "url": "https://github.com/NicholasCullenCooper/csaw/releases/download/v0.6.1/csaw_0.6.1_windows_arm64.zip",
            "bin": [
                "csaw.exe"
            ],
            "hash": "de77c1a0520b48f501df195ebf64af5fd81b7178743d4e9614db605103bb44f7"
        }
    },
    "homepage": "https://github.com/NicholasCullenCooper/csaw",
    "license": "MIT",
    "description": "Mount, not install. AI workspace configuration from git-backed registries."
}
